whyhow_rbr/__init__.py
whyhow_rbr/embedding.py
whyhow_rbr/exceptions.py
whyhow_rbr/processing.py
whyhow_rbr/rag.py
whyhow_rbr/rag_milvus.py
rule_based_retrieval-0.1.4.dist-info/LICENCE.md
rule_based_retrieval-0.1.4.dist-info/METADATA
rule_based_retrieval-0.1.4.dist-info/WHEEL
rule_based_retrieval-0.1.4.dist-info/top_level.txt
rule_based_retrieval-0.1.4.dist-info/RECORD
